cltcache/__init__.py
cltcache/cltcache.py
cltcache-1.2.2.dist-info/LICENSE
cltcache-1.2.2.dist-info/METADATA
cltcache-1.2.2.dist-info/WHEEL
cltcache-1.2.2.dist-info/entry_points.txt
cltcache-1.2.2.dist-info/top_level.txt
cltcache-1.2.2.dist-info/RECORD
