Metadata-Version: 2.1
Name: cltcache
Version: 1.2.2
Home-page: https://github.com/freedick/cltcache
Author: Fredrik Nordin
Author-email: freddan007@gmail.com
Classifier: Programming Language :: Python :: 3
Classifier: License :: OSI Approved :: MIT License
Classifier: Operating System :: POSIX
Requires-Python: >=3.6
License-File: LICENSE
